F2iBridge/F2iBridge.py
F2iBridge/__about__.py
F2iBridge/__init__.py
F2iBridge/__main__.py
F2iBridge/bridge_base.py
F2iBridge/bridge_canny.py
F2iBridge/bridge_i2i.py
F2iBridge/bridge_i2i_refine.py
F2iBridge/bridge_inpaint.py
F2iBridge/bridge_rewrite_line.py
F2iBridge/Workflow/__init__.py
F2iBridge/Workflow/canny.json
F2iBridge/Workflow/canny_api.json
F2iBridge/Workflow/image2image.json
F2iBridge/Workflow/image2image_api.json
F2iBridge/Workflow/mask_inpaint.json
F2iBridge/Workflow/mask_inpaint_api.json
f2ibridge-0.4.2.dist-info/METADATA
f2ibridge-0.4.2.dist-info/WHEEL
f2ibridge-0.4.2.dist-info/entry_points.txt
f2ibridge-0.4.2.dist-info/licenses/LICENSE
f2ibridge-0.4.2.dist-info/RECORD
