Metadata-Version: 2.4
Name: F2iBridge
Version: 0.4.2
Summary: image2image supporter
License-Expression: MIT
License-File: LICENSE
Requires-Python: <3.13,>=3.10
Requires-Dist: click>=8.1.7
Requires-Dist: fm-comfyui-bridge>=0.6.5
Requires-Dist: pillow>=11.0.0
Requires-Dist: pyyaml>=6.0.2
